matvis/__init__.py
matvis/_test_utils.py
matvis/_utils.py
matvis/cli.py
matvis/coordinates.py
matvis/wrapper.py
matvis/core/__init__.py
matvis/core/beams.py
matvis/core/coords.py
matvis/core/getz.py
matvis/core/matprod.py
matvis/core/tau.py
matvis/cpu/__init__.py
matvis/cpu/beams.py
matvis/cpu/coords.py
matvis/cpu/cpu.py
matvis/cpu/matprod.py
matvis/data/NF_HERA_Dipole_small.fits
matvis/gpu/__init__.py
matvis/gpu/_cublas.py
matvis/gpu/beams.py
matvis/gpu/coords.py
matvis/gpu/gpu.py
matvis/gpu/matprod.py
matvis/gpu_src/beam_interpolation.cu
matvis/gpu_src/measurement_equation.cu
matvis-1.3.2.dist-info/licenses/LICENSE.txt
matvis-1.3.2.dist-info/METADATA
matvis-1.3.2.dist-info/WHEEL
matvis-1.3.2.dist-info/entry_points.txt
matvis-1.3.2.dist-info/top_level.txt
matvis-1.3.2.dist-info/RECORD
