Metadata-Version: 2.4
Name: matvis
Version: 1.3.2
Summary: Fast matrix-based visibility simulator with interface to CPU and GPU
Home-page: https://github.com/hera-team/matvis
Author: HERA-Team
Author-email: steven.g.murray@asu.edu
License: MIT
Platform: any
Classifier: Development Status :: 4 - Beta
Classifier: Programming Language :: Python
Classifier: Programming Language :: Python :: 3
Classifier: Programming Language :: Python :: 3 :: Only
Requires-Python: >=3.10
License-File: LICENSE.txt
Requires-Dist: astropy
Requires-Dist: click
Requires-Dist: docstring-parser
Requires-Dist: line-profiler
Requires-Dist: numpy>=2.0
Requires-Dist: psutil
Requires-Dist: pyuvdata>=3.2.0
Requires-Dist: rich
Requires-Dist: scipy
Provides-Extra: all
Requires-Dist: matvis[dev,gpu,profile]; extra == "all"
Provides-Extra: dev
Requires-Dist: matvis[docs,test]; extra == "dev"
Provides-Extra: docs
Requires-Dist: furo; extra == "docs"
Requires-Dist: ipython; extra == "docs"
Requires-Dist: nbsphinx; extra == "docs"
Requires-Dist: numpydoc; extra == "docs"
Requires-Dist: sphinx; extra == "docs"
Provides-Extra: gpu
Requires-Dist: cupy; extra == "gpu"
Requires-Dist: jinja2; extra == "gpu"
Provides-Extra: profile
Requires-Dist: click; extra == "profile"
Requires-Dist: line-profiler; extra == "profile"
Requires-Dist: pyuvsim>=1.2.5; extra == "profile"
Provides-Extra: test
Requires-Dist: astropy-healpix; extra == "test"
Requires-Dist: hypothesis; extra == "test"
Requires-Dist: ipython; extra == "test"
Requires-Dist: matplotlib; extra == "test"
Requires-Dist: pyradiosky; extra == "test"
Requires-Dist: pytest; extra == "test"
Requires-Dist: pytest-cov; extra == "test"
Requires-Dist: pytest-lazy-fixtures; extra == "test"
Requires-Dist: pyuvsim[sim]>=1.2.5; extra == "test"
Dynamic: license-file
